{
	"schemaVersion": 1,
	"id": "bambootweaks",
	"version": "${version}",
	"name": "Bamboo Tweaks",
	"description": "Because bamboo needs some more uses.",
	"authors": [
		"vini2003"
	],
	"contact": {
		"sources": "https://github.com/vini2003/BambooTweaks"
	},
	"license": "GPLv3",
	"icon": "assets/bambootweaks/icon.png",
	"environment": "*",
	"entrypoints": {
		"main": [
			"dev.vini2003.bambootweaks.FabricBambooTweaks"
		],
		"client": [
			"dev.vini2003.bambootweaks.FabricBambooTweaksClient"
		]
	},
	"mixins": [
	],
	"depends": {
		"fabricloader": ">=0.7.0",
		"fabric": "*",
		"architectury": ">=1.8.131"
	},
	"suggests": {
		"flamingo": "*"
	}
}
